pinecore/__init__.py
pinecore/object.py
pinecore/patterns/__init__.py
pinecore/patterns/creational/__init__.py
pinecore/patterns/creational/singleton.py
pinecore/utils/__init__.py
pinecore/utils/logging/__init__.py
pinecore/utils/logging/stdout.py
pinecore/utils/pkg/__init__.py
pinecore/utils/pkg/gitversion.py
pinecore/utils/resources/__init__.py
pinecore/utils/resources/datares.py
pinecore/utils/resources/imageres.py
pinecore/utils/resources/loaders.py
pinecore/utils/resources/rawres.py
pinecore-0.0.1.dist-info/LICENSE
pinecore-0.0.1.dist-info/METADATA
pinecore-0.0.1.dist-info/WHEEL
pinecore-0.0.1.dist-info/top_level.txt
pinecore-0.0.1.dist-info/zip-safe
pinecore-0.0.1.dist-info/RECORD
